double_elimination/__init__.py
double_elimination/match.py
double_elimination/participant.py
double_elimination/tournament.py
double_elimination-1.4.1.dist-info/LICENSE
double_elimination-1.4.1.dist-info/METADATA
double_elimination-1.4.1.dist-info/WHEEL
double_elimination-1.4.1.dist-info/top_level.txt
double_elimination-1.4.1.dist-info/RECORD
