Metadata-Version: 2.1
Name: double-elimination
Version: 1.4.1
Summary: A double elimination tournament match handler.
Home-page: https://github.com/smwa/double_elimination
Author: Michael Smith
Author-email: michael.smith.ok@gmail.com
Classifier: Programming Language :: Python :: 3
Classifier: License :: OSI Approved :: MIT License
Classifier: Operating System :: OS Independent
Requires-Python: >=3.6
License-File: LICENSE
